dotenv2k8s/__init__.py
dotenv2k8s/main.py
dotenv2k8s-1.0.0.data/scripts/dotenv2k8s
dotenv2k8s-1.0.0.dist-info/METADATA
dotenv2k8s-1.0.0.dist-info/WHEEL
dotenv2k8s-1.0.0.dist-info/top_level.txt
dotenv2k8s-1.0.0.dist-info/RECORD
