Metadata-Version: 2.1
Name: dotenv2k8s
Version: 1.0.0
Summary: Command Line to export dotenv files to Kubernetes Secrets declarative manifests
Home-page: https://github.com/juliosmelo/dotenv2k8s
Author: juliocsmelo@gmail.com
License: Apache License 2.0
Project-URL: Source, https://github.com/juliosmelo/dotenv2k8s
Classifier: Development Status :: 5 - Production/Stable
Classifier: Intended Audience :: Developers
Classifier: Intended Audience :: System Administrators
Classifier: Natural Language :: English
Classifier: License :: OSI Approved :: Apache Software License
Classifier: Programming Language :: Python
Classifier: Programming Language :: Python :: 3
Classifier: Programming Language :: Python :: 3.7
Requires-Python: >= 3.7
Requires-Dist: click (==8.1.3)
Requires-Dist: python-dotenv (==0.20.0)
Requires-Dist: PyYAML (==6.0)
